netpercolate/__init__.py
netpercolate/evaluation.py
netpercolate/miscel.py
netpercolate/sequential_percolation.py
netpercolate/viz.py
netpercolate-0.1.1.dist-info/METADATA
netpercolate-0.1.1.dist-info/WHEEL
netpercolate-0.1.1.dist-info/top_level.txt
netpercolate-0.1.1.dist-info/RECORD
